LICENSE
MANIFEST.in
README.md
VERSION
setup.py
tkinter_map.egg-info/PKG-INFO
tkinter_map.egg-info/SOURCES.txt
tkinter_map.egg-info/dependency_links.txt
tkinter_map.egg-info/top_level.txt
tkmap/__init__.py
tkmap/bio.py
tkmap/model.py
tkmap/widget.py
tkmap/.json/google-map.json
tkmap/.json/google-satellite.json
tkmap/.json/mapbox-satellite-2x.json
tkmap/.json/mapbox-satellite.json
tkmap/.json/openstreetmap.json